{
	"class" : {
		"withAddress:" : "DamienPollet 9/1/2015 14:48:45" },
	"instance" : {
		"address" : "DamienPollet 9/1/2015 14:48:45",
		"arrivedPackets" : "DamienPollet 9/2/2015 17:05",
		"attach:" : "DamienPollet 9/1/2015 14:48:45",
		"consume:" : "DamienPollet 9/2/2015 17:03",
		"forward:from:" : "DamienPollet 9/2/2015 15:34",
		"hasLinkTo:" : "DamienPollet 9/1/2015 14:48:45",
		"hasReceived:" : "DamienPollet 9/2/2015 17:03",
		"initializeAddress:" : "DamienPollet 9/2/2015 17:03",
		"linksTowards:do:" : "DamienPollet 9/1/2015 14:58",
		"loopback" : "DamienPollet 9/1/2015 14:59",
		"printOn:" : "DamienPollet 9/1/2015 14:48:45",
		"receive:from:" : "DamienPollet 9/2/2015 14:57",
		"send:" : "DamienPollet 9/1/2015 14:48:45",
		"send:via:" : "DamienPollet 9/1/2015 14:48:45" } }
